License.txt
emgraph/__init__.py
emgraph/datasets/__init__.py
emgraph/datasets/abstract_dataset_adapter.py
emgraph/datasets/datasets.py
emgraph/datasets/numpy_adapter.py
emgraph/datasets/oneton_adapter.py
emgraph/datasets/sqlite_adapter.py
emgraph/evaluation/__init__.py
emgraph/evaluation/metrics.py
emgraph/evaluation/protocol.py
emgraph/experimental/__init__.py
emgraph/experimental/core/__init__.py
emgraph/experimental/core/convert.py
emgraph/experimental/core/graph.py
emgraph/initializers/__init__.py
emgraph/initializers/_initializer_constants.py
emgraph/initializers/constant.py
emgraph/initializers/glorot_uniform.py
emgraph/initializers/initializer.py
emgraph/initializers/random_normal.py
emgraph/initializers/random_uniform.py
emgraph/initializers/utils.py
emgraph/layers/__init__.py
emgraph/layers/pooling.py
emgraph/losses/__init__.py
emgraph/losses/_loss_constants.py
emgraph/losses/absolute_margin.py
emgraph/losses/bce.py
emgraph/losses/loss.py
emgraph/losses/nll.py
emgraph/losses/nll_multiclass.py
emgraph/losses/pairwise.py
emgraph/losses/self_adversarial.py
emgraph/losses/utils.py
emgraph/models/ComplEx.py
emgraph/models/ConvE.py
emgraph/models/ConvKB.py
emgraph/models/DistMult.py
emgraph/models/EmbeddingModel.py
emgraph/models/HolE.py
emgraph/models/RandomBaseline.py
emgraph/models/TransE.py
emgraph/models/__init__.py
emgraph/regularizers/__init__.py
emgraph/regularizers/_regularizer_constants.py
emgraph/regularizers/lp.py
emgraph/regularizers/regularizer.py
emgraph/regularizers/utils.py
emgraph/training/__init__.py
emgraph/training/_optimizer_constants.py
emgraph/training/adagrad.py
emgraph/training/adam.py
emgraph/training/momentum.py
emgraph/training/optimizer.py
emgraph/training/sgd.py
emgraph/training/utils.py
emgraph/utils/__init__.py
emgraph/utils/constants.py
emgraph/utils/misc.py
emgraph/utils/model_utils.py
emgraph-1.0.0rc1.dist-info/WHEEL
emgraph-1.0.0rc1.dist-info/METADATA
emgraph-1.0.0rc1.dist-info/RECORD
