Metadata-Version: 2.1
Name: emgraph
Version: 1.0.0rc1
Summary: A Python library for knowledge graph representation learning (graph embedding)
Home-page: https://bi-graph.github.io/Emgraph
License: BSD
Keywords: tensorflow,python,graph,knowledge graph,representation learning,graph representation learning,deep learning
Author: Soran Ghaderi
Author-email: soran.gdr.cd@gmail.com
Maintainer: Soran Ghaderi
Maintainer-email: soran.gdr.cd@gmail.com
Requires-Python: >=3.10,<3.11
Classifier: Development Status :: 4 - Beta
Classifier: Intended Audience :: Developers
Classifier: License :: OSI Approved :: BSD License
Classifier: License :: Other/Proprietary License
Classifier: Operating System :: OS Independent
Classifier: Programming Language :: Python :: 3
Classifier: Programming Language :: Python :: 3.10
Classifier: Programming Language :: Python :: 3.11
Classifier: Programming Language :: Python :: 3.6
Classifier: Programming Language :: Python :: 3.7
Classifier: Programming Language :: Python :: 3.8
Classifier: Programming Language :: Python :: 3.9
Classifier: Topic :: Software Development :: Libraries :: Python Modules :: Deep Learning :: Graph Representation Learning :: Graph Embedding :: Graph :: Knowledge Graph
Requires-Dist: numpy (>=1.23.1,<2.0.0)
Requires-Dist: pandas (>=1.4.3,<2.0.0)
Requires-Dist: pydantic (>=1.9.1,<2.0.0)
Requires-Dist: pytest (>=7.1.2,<8.0.0)
Requires-Dist: rdflib (>=6.2.0,<7.0.0)
Requires-Dist: scipy (>=1.9.0,<2.0.0)
Requires-Dist: tensorflow-gpu @ tensorflow_gpu-2.8.0-cp310-cp310-manylinux2010_x86_64.whl
Requires-Dist: tqdm (>=4.64.0,<5.0.0)
Project-URL: Repository, https://github.com/bi-graph/Emgraph
